catline/__init__.py
catline/_version.py
catline/queue.py
catline/utils.py
catline/adapters/__init__.py
catline/adapters/json_adapter.py
catline/adapters/redis_adapter.py
catline-0.0.3.dist-info/LICENSE
catline-0.0.3.dist-info/METADATA
catline-0.0.3.dist-info/WHEEL
catline-0.0.3.dist-info/top_level.txt
catline-0.0.3.dist-info/RECORD
