Metadata-Version: 2.1
Name: catline
Version: 0.0.3
Summary: Simple job queue
Home-page: https://github.com/yupix/catline
Author: yupix
Author-email: yupi0982@outlook.jp
License: MIT
Classifier: Development Status :: 2 - Pre-Alpha
Classifier: Programming Language :: Python :: 3.11
Classifier: Natural Language :: Japanese
Classifier: License :: OSI Approved :: MIT License
Requires-Python: >=3.11, <4.0
License-File: LICENSE
Requires-Dist: versioneer
Provides-Extra: redis
Requires-Dist: redis ; extra == 'redis'
